<?xml version="1.0"?>
<!DOCTYPE hibernate-mapping
PUBLIC "-//Hibernate/Hibernate Mapping DTD 3.0//EN"
"http://hibernate.sourceforge.net/hibernate-mapping-3.0.dtd">

<hibernate-mapping>

	<class name="com.test.Category" table="categories">
		
		<id name="id" column="id" type="long">
			<generator class="increment"> <!-- 主键id的生成方式为自增 -->
			</generator>
		</id>
		
		<property name="name">
			<column name="name" length="15"></column>
		</property>		
		
		<set name="childCategories" cascade="all" inverse="true" >
			<key column="category_id"></key>
			<one-to-many class="com.test.Category"/>
		</set>
		
		<many-to-one name="parentCategory" column="category_id" class="com.test.Category">
		</many-to-one>
		
		
		
	</class>

</hibernate-mapping>

