<?xml version="1.0"?>
<!DOCTYPE hibernate-mapping
PUBLIC "-//Hibernate/Hibernate Mapping DTD 3.0//EN"
"http://hibernate.sourceforge.net/hibernate-mapping-3.0.dtd">

<hibernate-mapping>

	<class name="com.test.Order" table="orders">
		
		<id name="id" column="id" type="long">
			<generator class="increment"> <!-- 主键id的生成方式为自增 -->
			</generator>
		</id>
		
		<property name="orderNumber" type="string">
			<column name="order_number" length="15"></column>
		</property>		

		<many-to-one name="customer" column="customer_id" class="com.test.Customer">
		</many-to-one>


	</class>

</hibernate-mapping>

